figma_export/__init__.py
figma_export/__main__.py
figma_export/exporters/AbstractExporter.py
figma_export/exporters/FontExporter.py
figma_export/exporters/ImageExporter.py
figma_export/exporters/ImagesetExporter.py
figma_export/exporters/__init__.py
figma_export/figma/FigmaClient.py
figma_export/figma/FigmaDocument.py
figma_export/figma/FigmaNode.py
figma_export/figma/FigmaRenderingResult.py
figma_export/figma/FigmaService.py
figma_export/figma/__init__.py
figma_export-0.1.dist-info/LICENSE
figma_export-0.1.dist-info/METADATA
figma_export-0.1.dist-info/WHEEL
figma_export-0.1.dist-info/entry_points.txt
figma_export-0.1.dist-info/top_level.txt
figma_export-0.1.dist-info/RECORD
