Metadata-Version: 2.1
Name: figma-export
Version: 0.1
Summary: Exports components from any Figma document and saves them to files that can be easily imported to other applications.
Home-page: https://github.com/RomanAliyev/figma-export
Author: Roman Aliyev
License: UNKNOWN
Platform: UNKNOWN
Classifier: Programming Language :: Python :: 3.7
Classifier: License :: OSI Approved :: MIT License
Classifier: Operating System :: OS Independent
Requires-Python: >=3.7
